{
  "content": [
    {
      "content": null,
      "created": "2022-06-21T02:23:49.600936Z",
      "format": null,
      "last_modified": "2022-06-21T02:22:31.691424Z",
      "mimetype": null,
      "name": "simple-operations.ipynb",
      "path": "xeus-sqlite/simple-operations.ipynb",
      "size": 20453,
      "type": "notebook",
      "writable": true
    }
  ],
  "created": "2022-06-21T02:23:49.600936Z",
  "format": "json",
  "last_modified": "2022-06-21T02:23:49.600936Z",
  "mimetype": null,
  "name": "xeus-sqlite",
  "path": "xeus-sqlite",
  "size": null,
  "type": "directory",
  "writable": true
}